{
  "id": "sum_of_two_numbers",
  "title": "Sum of Two Numbers",
  "difficulty": "easy",
  "description": "Write a function that returns the sum of two numbers.",
  "function_name": "solve",
  "constraints": [
    "The input will always be a list of exactly two numbers",
    "Numbers can be positive, negative, or zero",
    "Return type should match the sum of inputs"
  ],
  "test_cases": [
    {
      "input": {"a": 1, "b": 2},
      "output": 3
    },
    {
      "input": {"a": 5, "b": 10},
      "output": 15
    },
    {
      "input": {"a": -1, "b": 1},
      "output": 0
    },
    {
      "input": {"a": 0, "b": 0},
      "output": 0
    }
  ]
}
